pybela/Controller.py
pybela/Logger.py
pybela/Monitor.py
pybela/Streamer.py
pybela/Watcher.py
pybela/__init__.py
pybela/utils.py
pybela-2.0.3.dist-info/licenses/LICENSE
pybela-2.0.3.dist-info/METADATA
pybela-2.0.3.dist-info/WHEEL
pybela-2.0.3.dist-info/entry_points.txt
pybela-2.0.3.dist-info/top_level.txt
pybela-2.0.3.dist-info/RECORD
