Metadata-Version: 2.4
Name: pybela
Version: 2.0.3
Summary: pybela allows interfacing with the Bela embedded audio platform using python. It offers a convenient way to stream data between Bela and python, in both directions. In addition to data streaming, pybela supports data logging, as well as variable monitoring and control functionalities.
Author-email: Teresa Pelinski <teresapelinski@gmail.com>
License-Expression: LGPL-3.0
Project-URL: Homepage, https://github.com/BelaPlatform/pybela
Project-URL: Documentation, https://belaplatform.github.io/pybela/
Keywords: Bela,physical computing,data,audio,python,embedded systems,real-time,monitoring,control,streaming,sensor
Classifier: Programming Language :: Python :: 3
Classifier: Operating System :: OS Independent
Requires-Python: >=3.9
License-File: LICENSE
Requires-Dist: aiofiles==24.1.0
Requires-Dist: bitarray==3.0.0
Requires-Dist: bokeh==2.4.3
Requires-Dist: ipykernel==6.29.5
Requires-Dist: jupyter==1.1.1
Requires-Dist: jupyter-bokeh==3.0.5
Requires-Dist: matplotlib>=3.9.4
Requires-Dist: nest-asyncio==1.6.0
Requires-Dist: notebook==7.2.2
Requires-Dist: numpy==1.26.0
Requires-Dist: pandas==2.2.3
Requires-Dist: panel==0.14.4
Requires-Dist: paramiko==3.5.0
Requires-Dist: websockets==14.1
Provides-Extra: dev
Requires-Dist: build>=1.2.2.post1; extra == "dev"
Requires-Dist: pip-chill>=1.0.3; extra == "dev"
Requires-Dist: pipdeptree>=2.26.0; extra == "dev"
Requires-Dist: scipy>=1.13.1; extra == "dev"
Requires-Dist: sphinx==7.4.7; extra == "dev"
Requires-Dist: sphinx-rtd-theme==3.0.2; extra == "dev"
Requires-Dist: toml>=0.10.2; extra == "dev"
Requires-Dist: twine>=6.1.0; extra == "dev"
Requires-Dist: uvloop>=0.21.0; extra == "dev"
Dynamic: license-file
